[
  {
    "ContainingType": "SunTrack.API.Controllers.ProjectSectionController",
    "Method": "GetAllProjects",
    "RelativePath": "api/ProjectSection/GetAllProjects",
    "HttpMethod": "GET",
    "IsController": true,
    "Order": 0,
    "Parameters": [],
    "ReturnTypes": []
  },
  {
    "ContainingType": "SunTrack.API.Controllers.ProjectSectionController",
    "Method": "GetAllProjectsVM",
    "RelativePath": "api/ProjectSection/GetAllProjectsVM",
    "HttpMethod": "GET",
    "IsController": true,
    "Order": 0,
    "Parameters": [],
    "ReturnTypes": []
  },
  {
    "ContainingType": "SunTrack.API.Controllers.ProjectSectionController",
    "Method": "GetMappings",
    "RelativePath": "api/ProjectSection/GetMappings/{projectId}",
    "HttpMethod": "GET",
    "IsController": true,
    "Order": 0,
    "Parameters": [
      {
        "Name": "projectId",
        "Type": "System.Int32",
        "IsRequired": true
      }
    ],
    "ReturnTypes": []
  },
  {
    "ContainingType": "SunTrack.API.Controllers.ProjectSectionController",
    "Method": "GetProjectById",
    "RelativePath": "api/ProjectSection/GetProjectById",
    "HttpMethod": "GET",
    "IsController": true,
    "Order": 0,
    "Parameters": [
      {
        "Name": "id",
        "Type": "System.Int32",
        "IsRequired": false
      }
    ],
    "ReturnTypes": []
  },
  {
    "ContainingType": "SunTrack.API.Controllers.ProjectSectionController",
    "Method": "GetProjects",
    "RelativePath": "api/ProjectSection/GetProjects",
    "HttpMethod": "GET",
    "IsController": true,
    "Order": 0,
    "Parameters": [
      {
        "Name": "search",
        "Type": "SunTrack.API.ViewModels.SearchVM",
        "IsRequired": true
      }
    ],
    "ReturnTypes": []
  },
  {
    "ContainingType": "SunTrack.API.Controllers.ProjectSectionController",
    "Method": "GetProjectslist",
    "RelativePath": "api/ProjectSection/GetProjectslist",
    "HttpMethod": "GET",
    "IsController": true,
    "Order": 0,
    "Parameters": [],
    "ReturnTypes": []
  },
  {
    "ContainingType": "SunTrack.API.Controllers.ProjectSectionController",
    "Method": "SaveMapping",
    "RelativePath": "api/ProjectSection/SaveMapping",
    "HttpMethod": "POST",
    "IsController": true,
    "Order": 0,
    "Parameters": [
      {
        "Name": "model",
        "Type": "SunTrack.API.ViewModels.ProjectProductMappingRequestDto",
        "IsRequired": true
      }
    ],
    "ReturnTypes": []
  },
  {
    "ContainingType": "SunTrack.API.Controllers.ProjectSectionController",
    "Method": "SaveProject",
    "RelativePath": "api/ProjectSection/SaveProject",
    "HttpMethod": "POST",
    "IsController": true,
    "Order": 0,
    "Parameters": [
      {
        "Name": "model",
        "Type": "SunTrack.API.ViewModels.ProjectRequestDto",
        "IsRequired": true
      }
    ],
    "ReturnTypes": []
  }
]